<?xml version='1.1' encoding='UTF-8'?>
<jenkins.plugins.nodejs.tools.NodeJSInstallation_-DescriptorImpl plugin="nodejs@1.6.1">
  <installations>
    <jenkins.plugins.nodejs.tools.NodeJSInstallation>
      <name>NodeJS-20</name>
      <home></home>
      <properties>
        <jenkins.plugins.nodejs.tools.NodeJSInstallation$NodeJSInstaller>
          <id>20.18.0</id>
          <npmPackagesRefreshHours>72</npmPackagesRefreshHours>
        </jenkins.plugins.nodejs.tools.NodeJSInstallation$NodeJSInstaller>
      </properties>
    </jenkins.plugins.nodejs.tools.NodeJSInstallation>
  </installations>
</jenkins.plugins.nodejs.tools.NodeJSInstallation_-DescriptorImpl>